timer_module/__init__.py
timer_module/hasher.py
timer_module/logger.py
timer_module/metrics.py
timer_module/profiler.py
timer_module/terminal.py
timer_module/timer.py
timer_module-1.3.0.dist-info/LICENSE
timer_module-1.3.0.dist-info/METADATA
timer_module-1.3.0.dist-info/WHEEL
timer_module-1.3.0.dist-info/top_level.txt
timer_module-1.3.0.dist-info/RECORD
