Metadata-Version: 2.1
Name: timer-module
Version: 1.3.0
Summary: Timer Module with performance profiling features
Home-page: https://github.com/syn-chromatic/timer-module
Author: syn-chromatic
Author-email: synchromatic.github@gmail.com
License: UNKNOWN
Platform: UNKNOWN
Classifier: Development Status :: 5 - Production/Stable
Classifier: Programming Language :: Python :: 3.11
Classifier: Programming Language :: Python :: 3.10
Classifier: Topic :: Utilities
Requires-Python: >=3.10
License-File: LICENSE
Requires-Dist: setuptools (>=45.0)
